stock_tracker/__init__.py
stock_tracker/server.py
mcp_stock_tracker-0.1.1.dist-info/METADATA
mcp_stock_tracker-0.1.1.dist-info/WHEEL
mcp_stock_tracker-0.1.1.dist-info/entry_points.txt
mcp_stock_tracker-0.1.1.dist-info/licenses/LICENSE
mcp_stock_tracker-0.1.1.dist-info/RECORD
