Metadata-Version: 2.4
Name: mcp-stock-tracker
Version: 0.1.1
Summary: MCP server providing real-time stock price tracking with an interactive dashboard
Project-URL: Homepage, https://github.com/DOsinga/mcp_app_stocks
Project-URL: Documentation, https://github.com/DOsinga/mcp_app_stocks#readme
Project-URL: Repository, https://github.com/DOsinga/mcp_app_stocks
Project-URL: Issues, https://github.com/DOsinga/mcp_app_stocks/issues
Author-email: Douwe Osinga <douwe.osinga@gmail.com>
License: MIT
License-File: LICENSE
Keywords: dashboard,finance,mcp,real-time,stocks
Classifier: Development Status :: 3 - Alpha
Classifier: Intended Audience :: Developers
Classifier: License :: OSI Approved :: MIT License
Classifier: Programming Language :: Python :: 3
Classifier: Programming Language :: Python :: 3.10
Classifier: Programming Language :: Python :: 3.11
Classifier: Programming Language :: Python :: 3.12
Classifier: Topic :: Office/Business :: Financial
Classifier: Topic :: Software Development :: Libraries :: Python Modules
Requires-Python: >=3.10
Requires-Dist: fastmcp>=2.13
Requires-Dist: httpx>=0.24.0
Provides-Extra: dev
Requires-Dist: black>=23.0.0; extra == 'dev'
Requires-Dist: mypy>=1.0.0; extra == 'dev'
Requires-Dist: pytest-asyncio>=0.21.0; extra == 'dev'
Requires-Dist: pytest>=7.0.0; extra == 'dev'
Requires-Dist: ruff>=0.1.0; extra == 'dev'
